{
    "no_event": 0,
    "Ё": 1,
    "Выигрыш": 2,
    "Л": 3,
    "Религия": 4,
    "С": 5,
    "Смех": 6,
    "У": 7,
    "Х": 8,
    "активный": 9,
    "амбициозный": 10,
    "брюзжать": 11,
    "бутылка": 12,
    "бы": 13,
    "бывший": 14,
    "бык": 15,
    "быть": 16,
    "важный": 17,
    "влюбиться": 18,
    "восток": 19,
    "вредный; озорной": 20,
    "временный": 21,
    "гордый": 22,
    "дешёвый": 23,
    "доминантный": 24,
    "доминирующий": 25,
    "думать": 26,
    "еда": 27,
    "еще нет": 28,
    "женский туалет": 29,
    "жёсткий": 30,
    "зверь": 31,
    "знать": 32,
    "из-за": 33,
    "известный": 34,
    "изможденный": 35,
    "изношенный": 36,
    "иногда": 37,
    "интеллектуальный": 38,
    "календарь": 39,
    "кружка": 40,
    "лебедь": 41,
    "лошадь": 42,
    "любовный": 43,
    "магазин": 44,
    "между": 45,
    "месяц": 46,
    "минута": 47,
    "много": 48,
    "мотивация": 49,
    "мочь": 50,
    "наверху": 51,
    "наконец-то": 52,
    "напуганный": 53,
    "начало": 54,
    "начинать": 55,
    "не": 56,
    "неприятный": 57,
    "несколько": 58,
    "новый": 59,
    "носорог": 60,
    "оба": 61,
    "объятие": 62,
    "опытный": 63,
    "остановиться": 64,
    "отложить": 65,
    "переводить": 66,
    "платить": 67,
    "подлинный": 68,
    "поднос": 69,
    "подозревать": 70,
    "покаяние": 71,
    "помочь": 72,
    "потом": 73,
    "потрясающий": 74,
    "приличный": 75,
    "раздражать": 76,
    "рано": 77,
    "расстройство": 78,
    "самомнение": 79,
    "самоосознание": 80,
    "самопроверка": 81,
    "сегодня": 82,
    "седьмой": 83,
    "семь": 84,
    "сестра": 85,
    "сильный": 86,
    "синий": 87,
    "сожалеть": 88,
    "сорок": 89,
    "страсть": 90,
    "там": 91,
    "тот же самый (одинаковый)": 92,
    "тридцать": 93,
    "тёплый": 94,
    "упасть": 95,
    "худший": 96,
    "часто": 97,
    "человек": 98,
    "читать": 99,
    "язык": 100
}